mplfonts/__init__.py
mplfonts/bin/__init__.py
mplfonts/bin/cli.py
mplfonts/conf.py
mplfonts/fonts/NotoSansCJKsc-Regular.otf
mplfonts/fonts/NotoSansMonoCJKsc-Regular.otf
mplfonts/fonts/NotoSerifCJKsc-Regular.otf
mplfonts/fonts/SimHei.ttf
mplfonts/fonts/SourceHanMonoSC-Regular.otf
mplfonts/fonts/SourceHanSerifSC-Regular.otf
mplfonts/rc/matplotlibrc
mplfonts/util/__init__.py
mplfonts/util/common.py
mplfonts/util/manage.py
mplfonts-0.0.10.dist-info/LICENSE
mplfonts-0.0.10.dist-info/METADATA
mplfonts-0.0.10.dist-info/WHEEL
mplfonts-0.0.10.dist-info/entry_points.txt
mplfonts-0.0.10.dist-info/RECORD
