Metadata-Version: 2.1
Name: mplfonts
Version: 0.0.10
Summary: Fonts manager for matplotlib
Home-page: https://github.com/Clarmy/mplfonts
License: MIT
Keywords: matplotlib,fonts,manager
Author: Wentao Li
Author-email: clarmyleewt@outlook.com
Requires-Python: >=3.9
Classifier: License :: OSI Approved :: MIT License
Classifier: Programming Language :: Python :: 3
Classifier: Programming Language :: Python :: 3.9
Classifier: Programming Language :: Python :: 3.10
Classifier: Programming Language :: Python :: 3.11
Classifier: Programming Language :: Python :: 3.12
Classifier: Programming Language :: Python :: 3.13
Requires-Dist: fire (>=0.4.0)
Requires-Dist: fontmeta (>=1.6.1)
Requires-Dist: matplotlib (>=3.4)
Requires-Dist: numpy (>=1.26.0)
Project-URL: Repository, https://github.com/Clarmy/mplfonts
